Workbook

Sheet Export Summary
B3: This document was exported from Numbers. Each table was converted to an Excel worksheet. All other objects on each Numbers sheet were placed on separate worksheets. Please be aware that formula calculations may differ in Excel.
B7: Numbers Sheet Name | C7: Numbers Table Name | D7: Excel Worksheet Name
B9: Budgeting
C10: January | D10: Budgeting - January
C11: February | D11: Budgeting - February
C12: March | D12: Budgeting - March
C13: April | D13: Budgeting - April
C14: June | D14: Budgeting - June
C15: May | D15: Budgeting - May
C16: July | D16: Budgeting - July
C17: August | D17: Budgeting - August
C18: October | D18: Budgeting - October
C19: September | D19: Budgeting - September
C20: November | D20: Budgeting - November
C21: December | D21: Budgeting - December
C22: “All Drawings from the Sheet” | D22: Budgeting - Drawings

Sheet Budgeting - January
A1: January
A2: What | B2: Left over previous month | C2: Spend | D2: Budget | E2: Remaining
A3: Taxes | B3: 0 | E3: =SUM(B3:D3) -> 0
A4: Debts / Loans | B4: 0 | E4: =SUM(B4:D4) -> 0
A5: Production / Equipment | B5: 0 | E5: =SUM(B5:D5) -> 0
A6: Marketing | B6: 0 | E6: =SUM(B6:D6) -> 0
A7: Hired crew / Players | B7: 0 | E7: =SUM(B7:D7) -> 0
A8: Business Meals | B8: 0 | E8: =SUM(B8:D8) -> 0
A9: Subscriptions | B9: 0 | E9: =SUM(B9:D9) -> 0
A10: PD / Training / Event Tickets | B10: 0 | E10: =SUM(B10:D10) -> 0
A11: Equipment Rental | B11: 0 | E11: =SUM(B11:D11) -> 0
A12: Accommodations | B12: 0 | E12: =SUM(B12:D12) -> 0
A13: Transportation | B13: 0 | E13: =SUM(B13:D13) -> 0
A14: Insurance | B14: 0 | E14: =SUM(B14:D14) -> 0
... A18: Other | B18: 0 | E18: =SUM(B18:D18) -> 0

Sheet Budgeting - February
A1: February
A2: What | B2: Left over previous month | C2: Spend | D2: Budget | E2: Remaining
A3: Taxes | B3: =SUM('Budgeting - January'!B3:D3) -> 0 | E3: =SUM(B3:D3) -> 0
A4: Debts / Loans | B4: =SUM('Budgeting - January'!B4:D4) -> 0 | E4: =SUM(B4:D4) -> 0
A5: Production / Equipment | B5: =SUM('Budgeting - January'!B5:D5) -> 0 | E5: =SUM(B5:D5) -> 0
A6: Marketing | B6: =SUM('Budgeting - January'!B6:D6) -> 0 | E6: =SUM(B6:D6) -> 0
A7: Hired crew / Players | B7: =SUM('Budgeting - January'!B7:D7) -> 0 | E7: =SUM(B7:D7) -> 0
A8: Business Meals | B8: =SUM('Budgeting - January'!B8:D8) -> 0 | E8: =SUM(B8:D8) -> 0
A9: Subscriptions | B9: =SUM('Budgeting - January'!B9:D9) -> 0 | E9: =SUM(B9:D9) -> 0
A10: PD / Training / Event Tickets | B10: =SUM('Budgeting - January'!B10:D10) -> 0 | E10: =SUM(B10:D10) -> 0
A11: Equipment Rental | B11: =SUM('Budgeting - January'!B11:D11) -> 0 | E11: =SUM(B11:D11) -> 0
A12: Accommodations | B12: =SUM('Budgeting - January'!B12:D12) -> 0 | E12: =SUM(B12:D12) -> 0
A13: Transportation | B13: =SUM('Budgeting - January'!B13:D13) -> 0 | E13: =SUM(B13:D13) -> 0
A14: Insurance | B14: =SUM('Budgeting - January'!B14:D14) -> 0 | E14: =SUM(B14:D14) -> 0
... A18: Other | B18: =SUM('Budgeting - January'!B18:D18) -> 0 | E18: =SUM(B18:D18) -> 0

Sheet Budgeting - March
A1: March
A2: What | B2: Left over previous month | C2: Spend | D2: Budget | E2: Remaining
A3: Taxes | B3: =SUM('Budgeting - February'!B3:D3) -> 0 | E3: =SUM(B3:D3) -> 0
A4: Debts / Loans | B4: =SUM('Budgeting - February'!B4:D4) -> 0 | E4: =SUM(B4:D4) -> 0
A5: Production / Equipment | B5: =SUM('Budgeting - February'!B5:D5) -> 0 | E5: =SUM(B5:D5) -> 0
A6: Marketing | B6: =SUM('Budgeting - February'!B6:D6) -> 0 | E6: =SUM(B6:D6) -> 0
A7: Hired crew / Players | B7: =SUM('Budgeting - February'!B7:D7) -> 0 | E7: =SUM(B7:D7) -> 0
A8: Business Meals | B8: =SUM('Budgeting - February'!B8:D8) -> 0 | E8: =SUM(B8:D8) -> 0
A9: Subscriptions | B9: =SUM('Budgeting - February'!B9:D9) -> 0 | E9: =SUM(B9:D9) -> 0
A10: PD / Training / Event Tickets | B10: =SUM('Budgeting - February'!B10:D10) -> 0 | E10: =SUM(B10:D10) -> 0
A11: Equipment Rental | B11: =SUM('Budgeting - February'!B11:D11) -> 0 | E11: =SUM(B11:D11) -> 0
A12: Accommodations | B12: =SUM('Budgeting - February'!B12:D12) -> 0 | E12: =SUM(B12:D12) -> 0
A13: Transportation | B13: =SUM('Budgeting - February'!B13:D13) -> 0 | E13: =SUM(B13:D13) -> 0
A14: Insurance | B14: =SUM('Budgeting - February'!B14:D14) -> 0 | E14: =SUM(B14:D14) -> 0
... A18: Other | B18: =SUM('Budgeting - February'!B18:D18) -> 0 | E18: =SUM(B18:D18) -> 0

Sheet Budgeting - April
A1: April
A2: What | B2: Left over previous month | C2: Spend | D2: Budget | E2: Remaining
A3: Taxes | B3: =SUM('Budgeting - March'!B3:D3) -> 0 | E3: =SUM(B3:D3) -> 0
A4: Debts / Loans | B4: =SUM('Budgeting - March'!B4:D4) -> 0 | E4: =SUM(B4:D4) -> 0
A5: Production / Equipment | B5: =SUM('Budgeting - March'!B5:D5) -> 0 | E5: =SUM(B5:D5) -> 0
A6: Marketing | B6: =SUM('Budgeting - March'!B6:D6) -> 0 | E6: =SUM(B6:D6) -> 0
A7: Hired crew / Players | B7: =SUM('Budgeting - March'!B7:D7) -> 0 | E7: =SUM(B7:D7) -> 0
A8: Business Meals | B8: =SUM('Budgeting - March'!B8:D8) -> 0 | E8: =SUM(B8:D8) -> 0
A9: Subscriptions | B9: =SUM('Budgeting - March'!B9:D9) -> 0 | E9: =SUM(B9:D9) -> 0
A10: PD / Training / Event Tickets | B10: =SUM('Budgeting - March'!B10:D10) -> 0 | E10: =SUM(B10:D10) -> 0
A11: Equipment Rental | B11: =SUM('Budgeting - March'!B11:D11) -> 0 | E11: =SUM(B11:D11) -> 0
A12: Accommodations | B12: =SUM('Budgeting - March'!B12:D12) -> 0 | E12: =SUM(B12:D12) -> 0
A13: Transportation | B13: =SUM('Budgeting - March'!B13:D13) -> 0 | E13: =SUM(B13:D13) -> 0
A14: Insurance | B14: =SUM('Budgeting - March'!B14:D14) -> 0 | E14: =SUM(B14:D14) -> 0
... A18: Other | B18: =SUM('Budgeting - March'!B18:D18) -> 0 | E18: =SUM(B18:D18) -> 0

Sheet Budgeting - June
A1: June
A2: What | B2: Left over previous month | C2: Spend | D2: Budget | E2: Remaining
A3: Taxes | B3: =SUM('Budgeting - May'!B3:D3) -> 0 | E3: =SUM(B3:D3) -> 0
A4: Debts / Loans | B4: =SUM('Budgeting - May'!B4:D4) -> 0 | E4: =SUM(B4:D4) -> 0
A5: Production / Equipment | B5: =SUM('Budgeting - May'!B5:D5) -> 0 | E5: =SUM(B5:D5) -> 0
A6: Marketing | B6: =SUM('Budgeting - May'!B6:D6) -> 0 | E6: =SUM(B6:D6) -> 0
A7: Hired crew / Players | B7: =SUM('Budgeting - May'!B7:D7) -> 0 | E7: =SUM(B7:D7) -> 0
A8: Business Meals | B8: =SUM('Budgeting - May'!B8:D8) -> 0 | E8: =SUM(B8:D8) -> 0
A9: Subscriptions | B9: =SUM('Budgeting - May'!B9:D9) -> 0 | E9: =SUM(B9:D9) -> 0
A10: PD / Training / Event Tickets | B10: =SUM('Budgeting - May'!B10:D10) -> 0 | E10: =SUM(B10:D10) -> 0
A11: Equipment Rental | B11: =SUM('Budgeting - May'!B11:D11) -> 0 | E11: =SUM(B11:D11) -> 0
A12: Accommodations | B12: =SUM('Budgeting - May'!B12:D12) -> 0 | E12: =SUM(B12:D12) -> 0
A13: Transportation | B13: =SUM('Budgeting - May'!B13:D13) -> 0 | E13: =SUM(B13:D13) -> 0
A14: Insurance | B14: =SUM('Budgeting - May'!B14:D14) -> 0 | E14: =SUM(B14:D14) -> 0
... A18: Other | B18: =SUM('Budgeting - May'!B18:D18) -> 0 | E18: =SUM(B18:D18) -> 0

Sheet Budgeting - May
A1: May
A2: What | B2: Left over previous month | C2: Spend | D2: Budget | E2: Remaining
A3: Taxes | B3: =SUM('Budgeting - April'!B3:D3) -> 0 | E3: =SUM(B3:D3) -> 0
A4: Debts / Loans | B4: =SUM('Budgeting - April'!B4:D4) -> 0 | E4: =SUM(B4:D4) -> 0
A5: Production / Equipment | B5: =SUM('Budgeting - April'!B5:D5) -> 0 | E5: =SUM(B5:D5) -> 0
A6: Marketing | B6: =SUM('Budgeting - April'!B6:D6) -> 0 | E6: =SUM(B6:D6) -> 0
A7: Hired crew / Players | B7: =SUM('Budgeting - April'!B7:D7) -> 0 | E7: =SUM(B7:D7) -> 0
A8: Business Meals | B8: =SUM('Budgeting - April'!B8:D8) -> 0 | E8: =SUM(B8:D8) -> 0
A9: Subscriptions | B9: =SUM('Budgeting - April'!B9:D9) -> 0 | E9: =SUM(B9:D9) -> 0
A10: PD / Training / Event Tickets | B10: =SUM('Budgeting - April'!B10:D10) -> 0 | E10: =SUM(B10:D10) -> 0
A11: Equipment Rental | B11: =SUM('Budgeting - April'!B11:D11) -> 0 | E11: =SUM(B11:D11) -> 0
A12: Accommodations | B12: =SUM('Budgeting - April'!B12:D12) -> 0 | E12: =SUM(B12:D12) -> 0
A13: Transportation | B13: =SUM('Budgeting - April'!B13:D13) -> 0 | E13: =SUM(B13:D13) -> 0
A14: Insurance | B14: =SUM('Budgeting - April'!B14:D14) -> 0 | E14: =SUM(B14:D14) -> 0
... A18: Other | B18: =SUM('Budgeting - April'!B18:D18) -> 0 | E18: =SUM(B18:D18) -> 0

Sheet Budgeting - July
A1: July
A2: What | B2: Left over previous month | C2: Spend | D2: Budget | E2: Remaining
A3: Taxes | B3: =SUM('Budgeting - June'!B3:D3) -> 0 | E3: =SUM(B3:D3) -> 0
A4: Debts / Loans | B4: =SUM('Budgeting - June'!B4:D4) -> 0 | E4: =SUM(B4:D4) -> 0
A5: Production / Equipment | B5: =SUM('Budgeting - June'!B5:D5) -> 0 | E5: =SUM(B5:D5) -> 0
A6: Marketing | B6: =SUM('Budgeting - June'!B6:D6) -> 0 | E6: =SUM(B6:D6) -> 0
A7: Hired crew / Players | B7: =SUM('Budgeting - June'!B7:D7) -> 0 | E7: =SUM(B7:D7) -> 0
A8: Business Meals | B8: =SUM('Budgeting - June'!B8:D8) -> 0 | E8: =SUM(B8:D8) -> 0
A9: Subscriptions | B9: =SUM('Budgeting - June'!B9:D9) -> 0 | E9: =SUM(B9:D9) -> 0
A10: PD / Training / Event Tickets | B10: =SUM('Budgeting - June'!B10:D10) -> 0 | E10: =SUM(B10:D10) -> 0
A11: Equipment Rental | B11: =SUM('Budgeting - June'!B11:D11) -> 0 | E11: =SUM(B11:D11) -> 0
A12: Accommodations | B12: =SUM('Budgeting - June'!B12:D12) -> 0 | E12: =SUM(B12:D12) -> 0
A13: Transportation | B13: =SUM('Budgeting - June'!B13:D13) -> 0 | E13: =SUM(B13:D13) -> 0
A14: Insurance | B14: =SUM('Budgeting - June'!B14:D14) -> 0 | E14: =SUM(B14:D14) -> 0
... A18: Other | B18: =SUM('Budgeting - June'!B18:D18) -> 0 | E18: =SUM(B18:D18) -> 0

Sheet Budgeting - August
A1: August
A2: What | B2: Left over previous month | C2: Spend | D2: Budget | E2: Remaining
A3: Taxes | B3: =SUM('Budgeting - July'!B3:D3) -> 0 | E3: =SUM(B3:D3) -> 0
A4: Debts / Loans | B4: =SUM('Budgeting - July'!B4:D4) -> 0 | E4: =SUM(B4:D4) -> 0
A5: Production / Equipment | B5: =SUM('Budgeting - July'!B5:D5) -> 0 | E5: =SUM(B5:D5) -> 0
A6: Marketing | B6: =SUM('Budgeting - July'!B6:D6) -> 0 | E6: =SUM(B6:D6) -> 0
A7: Hired crew / Players | B7: =SUM('Budgeting - July'!B7:D7) -> 0 | E7: =SUM(B7:D7) -> 0
A8: Business Meals | B8: =SUM('Budgeting - July'!B8:D8) -> 0 | E8: =SUM(B8:D8) -> 0
A9: Subscriptions | B9: =SUM('Budgeting - July'!B9:D9) -> 0 | E9: =SUM(B9:D9) -> 0
A10: PD / Training / Event Tickets | B10: =SUM('Budgeting - July'!B10:D10) -> 0 | E10: =SUM(B10:D10) -> 0
A11: Equipment Rental | B11: =SUM('Budgeting - July'!B11:D11) -> 0 | E11: =SUM(B11:D11) -> 0
A12: Accommodations | B12: =SUM('Budgeting - July'!B12:D12) -> 0 | E12: =SUM(B12:D12) -> 0
A13: Transportation | B13: =SUM('Budgeting - July'!B13:D13) -> 0 | E13: =SUM(B13:D13) -> 0
A14: Insurance | B14: =SUM('Budgeting - July'!B14:D14) -> 0 | E14: =SUM(B14:D14) -> 0
... A18: Other | B18: =SUM('Budgeting - July'!B18:D18) -> 0 | E18: =SUM(B18:D18) -> 0

Sheet Budgeting - October
A1: October
A2: What | B2: Left over previous month | C2: Spend | D2: Budget | E2: Remaining
A3: Taxes | B3: =SUM('Budgeting - September'!B3:D3) -> 0 | E3: =SUM(B3:D3) -> 0
A4: Debts / Loans | B4: =SUM('Budgeting - September'!B4:D4) -> 0 | E4: =SUM(B4:D4) -> 0
A5: Production / Equipment | B5: =SUM('Budgeting - September'!B5:D5) -> 0 | E5: =SUM(B5:D5) -> 0
A6: Marketing | B6: =SUM('Budgeting - September'!B6:D6) -> 0 | E6: =SUM(B6:D6) -> 0
A7: Hired crew / Players | B7: =SUM('Budgeting - September'!B7:D7) -> 0 | E7: =SUM(B7:D7) -> 0
A8: Business Meals | B8: =SUM('Budgeting - September'!B8:D8) -> 0 | E8: =SUM(B8:D8) -> 0
A9: Subscriptions | B9: =SUM('Budgeting - September'!B9:D9) -> 0 | E9: =SUM(B9:D9) -> 0
A10: PD / Training / Event Tickets | B10: =SUM('Budgeting - September'!B10:D10) -> 0 | E10: =SUM(B10:D10) -> 0
A11: Equipment Rental | B11: =SUM('Budgeting - September'!B11:D11) -> 0 | E11: =SUM(B11:D11) -> 0
A12: Accommodations | B12: =SUM('Budgeting - September'!B12:D12) -> 0 | E12: =SUM(B12:D12) -> 0
A13: Transportation | B13: =SUM('Budgeting - September'!B13:D13) -> 0 | E13: =SUM(B13:D13) -> 0
A14: Insurance | B14: =SUM('Budgeting - September'!B14:D14) -> 0 | E14: =SUM(B14:D14) -> 0
... A18: Other | B18: =SUM('Budgeting - September'!B18:D18) -> 0 | E18: =SUM(B18:D18) -> 0

Sheet Budgeting - September
A1: September
A2: What | B2: Left over previous month | C2: Spend | D2: Budget | E2: Remaining
A3: Taxes | B3: =SUM('Budgeting - August'!B3:D3) -> 0 | E3: =SUM(B3:D3) -> 0
A4: Debts / Loans | B4: =SUM('Budgeting - August'!B4:D4) -> 0 | E4: =SUM(B4:D4) -> 0
A5: Production / Equipment | B5: =SUM('Budgeting - August'!B5:D5) -> 0 | E5: =SUM(B5:D5) -> 0
A6: Marketing | B6: =SUM('Budgeting - August'!B6:D6) -> 0 | E6: =SUM(B6:D6) -> 0
A7: Hired crew / Players | B7: =SUM('Budgeting - August'!B7:D7) -> 0 | E7: =SUM(B7:D7) -> 0
A8: Business Meals | B8: =SUM('Budgeting - August'!B8:D8) -> 0 | E8: =SUM(B8:D8) -> 0
A9: Subscriptions | B9: =SUM('Budgeting - August'!B9:D9) -> 0 | E9: =SUM(B9:D9) -> 0
A10: PD / Training / Event Tickets | B10: =SUM('Budgeting - August'!B10:D10) -> 0 | E10: =SUM(B10:D10) -> 0
A11: Equipment Rental | B11: =SUM('Budgeting - August'!B11:D11) -> 0 | E11: =SUM(B11:D11) -> 0
A12: Accommodations | B12: =SUM('Budgeting - August'!B12:D12) -> 0 | E12: =SUM(B12:D12) -> 0
A13: Transportation | B13: =SUM('Budgeting - August'!B13:D13) -> 0 | E13: =SUM(B13:D13) -> 0
A14: Insurance | B14: =SUM('Budgeting - August'!B14:D14) -> 0 | E14: =SUM(B14:D14) -> 0
... A18: Other | B18: =SUM('Budgeting - August'!B18:D18) -> 0 | E18: =SUM(B18:D18) -> 0

Sheet Budgeting - November
A1: November
A2: What | B2: Left over previous month | C2: Spend | D2: Budget | E2: Remaining
A3: Taxes | B3: =SUM('Budgeting - October'!B3:D3) -> 0 | E3: =SUM(B3:D3) -> 0
A4: Debts / Loans | B4: =SUM('Budgeting - October'!B4:D4) -> 0 | E4: =SUM(B4:D4) -> 0
A5: Production / Equipment | B5: =SUM('Budgeting - October'!B5:D5) -> 0 | E5: =SUM(B5:D5) -> 0
A6: Marketing | B6: =SUM('Budgeting - October'!B6:D6) -> 0 | E6: =SUM(B6:D6) -> 0
A7: Hired crew / Players | B7: =SUM('Budgeting - October'!B7:D7) -> 0 | E7: =SUM(B7:D7) -> 0
A8: Business Meals | B8: =SUM('Budgeting - October'!B8:D8) -> 0 | E8: =SUM(B8:D8) -> 0
A9: Subscriptions | B9: =SUM('Budgeting - October'!B9:D9) -> 0 | E9: =SUM(B9:D9) -> 0
A10: PD / Training / Event Tickets | B10: =SUM('Budgeting - October'!B10:D10) -> 0 | E10: =SUM(B10:D10) -> 0
A11: Equipment Rental | B11: =SUM('Budgeting - October'!B11:D11) -> 0 | E11: =SUM(B11:D11) -> 0
A12: Accommodations | B12: =SUM('Budgeting - October'!B12:D12) -> 0 | E12: =SUM(B12:D12) -> 0
A13: Transportation | B13: =SUM('Budgeting - October'!B13:D13) -> 0 | E13: =SUM(B13:D13) -> 0
A14: Insurance | B14: =SUM('Budgeting - October'!B14:D14) -> 0 | E14: =SUM(B14:D14) -> 0
... A18: Other | B18: =SUM('Budgeting - October'!B18:D18) -> 0 | E18: =SUM(B18:D18) -> 0

Sheet Budgeting - December
A1: December
A2: What | B2: Left over previous month | C2: Spend | D2: Budget | E2: Remaining
A3: Taxes | B3: =SUM('Budgeting - November'!B3:D3) -> 0 | E3: =SUM(B3:D3) -> 0
A4: Debts / Loans | B4: =SUM('Budgeting - November'!B4:D4) -> 0 | E4: =SUM(B4:D4) -> 0
A5: Production / Equipment | B5: =SUM('Budgeting - November'!B5:D5) -> 0 | E5: =SUM(B5:D5) -> 0
A6: Marketing | B6: =SUM('Budgeting - November'!B6:D6) -> 0 | E6: =SUM(B6:D6) -> 0
A7: Hired crew / Players | B7: =SUM('Budgeting - November'!B7:D7) -> 0 | E7: =SUM(B7:D7) -> 0
A8: Business Meals | B8: =SUM('Budgeting - November'!B8:D8) -> 0 | E8: =SUM(B8:D8) -> 0
A9: Subscriptions | B9: =SUM('Budgeting - November'!B9:D9) -> 0 | E9: =SUM(B9:D9) -> 0
A10: PD / Training / Event Tickets | B10: =SUM('Budgeting - November'!B10:D10) -> 0 | E10: =SUM(B10:D10) -> 0
A11: Equipment Rental | B11: =SUM('Budgeting - November'!B11:D11) -> 0 | E11: =SUM(B11:D11) -> 0
A12: Accommodations | B12: =SUM('Budgeting - November'!B12:D12) -> 0 | E12: =SUM(B12:D12) -> 0
A13: Transportation | B13: =SUM('Budgeting - November'!B13:D13) -> 0 | E13: =SUM(B13:D13) -> 0
A14: Insurance | B14: =SUM('Budgeting - November'!B14:D14) -> 0 | E14: =SUM(B14:D14) -> 0
... A18: Other | B18: =SUM('Budgeting - November'!B18:D18) -> 0 | E18: =SUM(B18:D18) -> 0

Sheet Budgeting - Drawings
