Workbook

Sheet Export Summary
B3: This document was exported from Numbers. Each table was converted to an Excel worksheet. All other objects on each Numbers sheet were placed on separate worksheets. Please be aware that formula calculations may differ in Excel.
B7: Numbers Sheet Name | C7: Numbers Table Name | D7: Excel Worksheet Name
B9: Revenue & Lost Tracker
C10: Income | D10: Revenue & Lost Tracker - Income
C11: Spending | D11: Revenue & Lost Tracker - Spendi
C12: Quarters | D12: Revenue & Lost Tracker - Quarte
C13: “All Drawings from the Sheet” | D13: Revenue & Lost Tracker - Drawin

Sheet Revenue & Lost Tracker - Income
A1: Income
B2: Week 1 | C2: Week 2 | D2: Week 3 | E2: Week 4 | F2: Week 5 | G2: Week 6 | H2: Week 7 | I2: Week 8 | J2: Week 9 | K2: Week 10 | L2: Week 11 | M2: Week 12 | N2: Week 13 | O2: Week 14 | P2: Week 15 | Q2: Week 16 | R2: Week 17 | S2: Week 18 | T2: Week 19 | U2: Week 20 | V2: Week 21 | W2: Week 22 | X2: Week 23 | Y2: Week 24 | Z2: Week 25 | AA2: Week 26 | AB2: Week 27 | AC2: Week 28 | AD2: Week 29 | AE2: Week 30 | AF2: Week 31 | AG2: Week 32 | AH2: Week 33 | AI2: Week 34 | AJ2: Week 35 | AK2: Week 36 | AL2: Week 37 | AM2: Week 38 | AN2: Week 39 | AO2: Week 40 | AP2: Week 41 | AQ2: Week 42 | AR2: Week 43 | AS2: Week 44 | AT2: Week 45 | AU2: Week 46 | AV2: Week 47 | AW2: Week 48 | AX2: Week 49 | AY2: Week 50 | AZ2: Week 51 | BA2: Week 52 | BB2: Total A Year
A3: Bookings | BB3: =SUM(B3:BA3) -> 0
A4: Royalties / Monetization | BB4: =SUM(B4:BA4) -> 0
A5: Teaching | BB5: =SUM(B5:BA5) -> 0
A6: Merchendise | BB6: =SUM(B6:BA6) -> 0
A7: Brand Collaborations | BB7: =SUM(B7:BA7) -> 0
A8: Crowdfunding Campain | BB8: =SUM(B8:BA8) -> 0
A9: Music Writing | BB9: =SUM(B9:BA9) -> 0
A10: Other | BB10: =SUM(B10:BA10) -> 0
A12: Week Total | B12: =SUM(B3:B10) -> 0 | C12: =SUM(C3:C10) -> 0 | D12: =SUM(D3:D10) -> 0 | E12: =SUM(E3:E10) -> 0 | F12: =SUM(F3:F10) -> 0 | G12: =SUM(G3:G10) -> 0 | H12: =SUM(H3:H10) -> 0 | I12: =SUM(I3:I10) -> 0 | ... BB12: =SUM(BB3:BB10) -> 0
A13: 4 Weeks Total | E13: =SUM(B12:E12) -> 0 | I13: =SUM(F12:I12) -> 0 | M13: =SUM(J12:M12) -> 0 | Q13: =SUM(N12:Q12) -> 0 | U13: =SUM(R12:U12) -> 0 | Y13: =SUM(V12:Y12) -> 0 | AC13: =SUM(Z12:AC12) -> 0 | AG13: =SUM(AD12:AG12) -> 0 | AK13: =SUM(AH12:AK12) -> 0 | AO13: =SUM(AL12:AO12) -> 0 | AS13: =SUM(AP12:AS12) -> 0 | AW13: =SUM(AT12:AW12) -> 0 | BA13: =SUM(AX12:BA12) -> 0

Sheet Revenue & Lost Tracker - Spendi
A1: Spending
A2: Week | B2: Week 1 | C2: Week 2 | D2: Week 3 | E2: Week 4 | F2: Week 5 | G2: Week 6 | H2: Week 7 | I2: Week 8 | J2: Week 9 | K2: Week 10 | L2: Week 11 | M2: Week 12 | N2: Week 13 | O2: Week 14 | P2: Week 15 | Q2: Week 16 | R2: Week 17 | S2: Week 18 | T2: Week 19 | U2: Week 20 | V2: Week 21 | W2: Week 22 | X2: Week 23 | Y2: Week 24 | Z2: Week 25 | AA2: Week 26 | AB2: Week 27 | AC2: Week 28 | AD2: Week 29 | AE2: Week 30 | AF2: Week 31 | AG2: Week 32 | AH2: Week 33 | AI2: Week 34 | AJ2: Week 35 | AK2: Week 36 | AL2: Week 37 | AM2: Week 38 | AN2: Week 39 | AO2: Week 40 | AP2: Week 41 | AQ2: Week 42 | AR2: Week 43 | AS2: Week 44 | AT2: Week 45 | AU2: Week 46 | AV2: Week 47 | AW2: Week 48 | AX2: Week 49 | AY2: Week 50 | AZ2: Week 51 | BA2: Week 52 | BB2: Total A Year
A3: Savings | BB3: =SUM(B3:BA3) -> 0
A4: Debt / Loans | BB4: =SUM(B4:BA4) -> 0
A5: Taxes | BB5: =SUM(B5:BA5) -> 0
A6: Management Team | BB6: =SUM(B6:BA6) -> 0
A7: Agency | BB7: =SUM(B7:BA7) -> 0
A8: Production / Performance | BB8: =SUM(B8:BA8) -> 0
A9: Marketing | BB9: =SUM(B9:BA9) -> 0
A10: Hired Crew / Players | BB10: =SUM(B10:BA10) -> 0
A11: Business Meals | BB11: =SUM(B11:BA11) -> 0
A12: Subscriptions | BB12: =SUM(B12:BA12) -> 0
A13: PD / Training / Event Tickets | BB13: =SUM(B13:BA13) -> 0
A14: Equipment Rental | BB14: =SUM(B14:BA14) -> 0
... A22: Other | BB22: =SUM(B22:BA22) -> 0
A24: Week Total | B24: =SUM(B3:B22) -> 0 | C24: =SUM(C3:C22) -> 0 | D24: =SUM(D3:D22) -> 0 | E24: =SUM(E3:E22) -> 0 | F24: =SUM(F3:F22) -> 0 | G24: =SUM(G3:G22) -> 0 | H24: =SUM(H3:H22) -> 0 | I24: =SUM(I3:I22) -> 0 | ... BB24: =SUM(BB3:BB22) -> 0
A25: 4 Weeks Total | E25: =SUM(B24:E24) -> 0 | I25: =SUM(F24:I24) -> 0 | M25: =SUM(J24:M24) -> 0 | Q25: =SUM(N24:Q24) -> 0 | U25: =SUM(R24:U24) -> 0 | Y25: =SUM(V24:Y24) -> 0 | AC25: =SUM(Z24:AC24) -> 0 | AG25: =SUM(AD24:AG24) -> 0 | AK25: =SUM(AH24:AK24) -> 0 | AO25: =SUM(AL24:AO24) -> 0 | AS25: =SUM(AP24:AS24) -> 0 | AW25: =SUM(AT24:AW24) -> 0 | BA25: =SUM(AX24:BA24) -> 0

Sheet Revenue & Lost Tracker - Quarte
A1: Quarters
B2: Q1 | C2: Q2 | D2: Q3 | E2: Q4 | F2: Year
A3: Income | B3: =SUM('Revenue & Lost Tracker - Income'!E13,'Revenue & Lost Tracker - Income'!I13,'Revenue & Lost Tracker - Income'!M13) -> 0 | C3: =SUM('Revenue & Lost Tracker - Income'!Q13,'Revenue & Lost Tracker - Income'!U13,'Revenue & Lost Tracker - Income'!Y13) -> 0 | D3: =SUM('Revenue & Lost Tracker - Income'!AC13,'Revenue & Lost Tracker - Income'!AG13,'Revenue & Lost Tracker - Income'!AK13) -> 0 | E3: =SUM('Revenue & Lost Tracker - Income'!AO13,'Revenue & Lost Tracker - Income'!AS13,'Revenue & Lost Tracker - Income'!AW13,'Revenue & Lost Tracker - Income'!BA13) -> 0 | F3: =SUM(B3:E3) -> 0
A4: Spending | B4: =SUM('Revenue & Lost Tracker - Spendi'!E25,'Revenue & Lost Tracker - Spendi'!I25,'Revenue & Lost Tracker - Spendi'!M25) -> 0 | C4: =SUM('Revenue & Lost Tracker - Spendi'!Q25,'Revenue & Lost Tracker - Spendi'!U25,'Revenue & Lost Tracker - Spendi'!Y25) -> 0 | D4: =SUM('Revenue & Lost Tracker - Spendi'!AC25,'Revenue & Lost Tracker - Spendi'!AG25,'Revenue & Lost Tracker - Spendi'!AK25) -> 0 | E4: =SUM('Revenue & Lost Tracker - Spendi'!AO25,'Revenue & Lost Tracker - Spendi'!AS25,'Revenue & Lost Tracker - Spendi'!AW25,'Revenue & Lost Tracker - Spendi'!BA25) -> 0 | F4: =SUM(B4:E4) -> 0
A6: Profit / Lost | B6: =SUM(B3:B4) -> 0 | C6: =SUM(C3:C4) -> 0 | D6: =SUM(D3:D4) -> 0 | E6: =SUM(E3:E4) -> 0 | F6: =SUM(F3:F4) -> 0

Sheet Revenue & Lost Tracker - Drawin
